{
    "$schema": "http://schema.management.azure.com/schemas/2015-01-01/deploymentTemplate.json",
    "contentVersion": "1.0.0.0",
    "parameters": {
        "aseName": {
            "defaultValue": "ASE-TEST",
            "type": "String",
            "metadata": {
                "description": "Name of the App Service Environment"
            }
        },
        "aseLocation": {
            "defaultValue": "West Europe",
            "type": "String",
            "metadata": {
                "description": "Location of the App Service Environment"
            }
        },
        "APP-SPLANName": {
            "defaultValue": "ASE-APP-SERVICE-PLAN",
            "type": "String",
            "metadata": {
                "description": "App service plan name"
            }
        }
    },
    "variables": {
        "ASE-VNetPrefix": "10.0.0.0/16",
        "ASE-VNetSubnet1Name": "Subnet-1",
        "ASE-VNetSubnet1Prefix": "10.0.0.0/24",
        "ASE-VNET-Name": "[concat('ASE-VNET', uniqueString(resourceGroup().id))]",
        "WEB-APP-ASEv2Name": "[concat('WEB-APP-ASEv2', uniqueString(resourceGroup().id))]"
    },
    "resources": [
        {
            "type": "Microsoft.Network/virtualNetworks",
            "name": "[variables('ASE-VNET-Name')]",
            "apiVersion": "2016-03-30",
            "location": "[resourceGroup().location]",
            "tags": {
                "displayName": "ASE-VNET"
            },
            "properties": {
                "addressSpace": {
                    "addressPrefixes": [
                        "[variables('ASE-VNetPrefix')]"
                    ]
                },
                "subnets": [
                    {
                        "name": "[variables('ASE-VNetSubnet1Name')]",
                        "properties": {
                            "addressPrefix": "[variables('ASE-VNetSubnet1Prefix')]"
                        }
                    }
                ]
            },
            "dependsOn": []
        },
        {
            "type": "Microsoft.Web/hostingEnvironments",
            "kind": "ASEV2",
            "name": "[parameters('aseName')]",
            "apiVersion": "2015-08-01",
            "location": "[parameters('aseLocation')]",
            "properties": {
                "name": "[parameters('aseName')]",
                "location": "[parameters('aseLocation')]",
                "virtualNetwork": {
                    "Id": "[concat('/subscriptions/',subscription().subscriptionId,'/resourceGroups/',resourceGroup().name,'/providers/Microsoft.Network/virtualNetworks/', variables('ASE-VNET-Name'))]",
                    "Subnet": "[variables('ASE-VNETSubnet1Name')]"
                }
            },
            "dependsOn": [
                "[resourceId('Microsoft.Network/virtualNetworks', variables('ASE-VNET-Name'))]"
            ]
        },
        {
            "type": "Microsoft.Web/serverfarms",
            "sku": {
                "Tier": "Isolated",
                "Name": "I1"
            },
            "kind": "",
            "name": "[parameters('APP-SPLANName')]",
            "apiVersion": "2016-03-01",
            "location": "[parameters('aseLocation')]",
            "properties": {
                "name": "[parameters('APP-SPLANName')]",
                "workerSize": "Small",
                "workerSizeId": 0,
                "numberOfWorkers": 1,
                "reserved": false,
                "hostingEnvironment": "[parameters('aseName')]"
            },
            "dependsOn": [
                "[resourceId('Microsoft.Web/hostingEnvironments', parameters('aseName'))]"
            ]
        },
        {
            "type": "Microsoft.Web/sites",
            "name": "[variables('WEB-APP-ASEv2Name')]",
            "apiVersion": "2016-08-01",
            "location": "[resourceGroup().location]",
            "tags": {},
            "properties": {
                "name": "[variables('WEB-APP-ASEv2Name')]",
                "hostingEnvironmentProfile": {
                    "id": "[resourceId('Microsoft.Web/hostingEnvironments', parameters('aseName'))]"
                },
                "serverFarmId": "[resourceId('Microsoft.Web/serverfarms', parameters('APP-SPLANName'))]"
            },
            "dependsOn": [
                "[resourceId('Microsoft.Web/serverfarms', parameters('APP-SPLANName'))]",
                "[resourceId('Microsoft.Web/hostingEnvironments', parameters('aseName'))]"
            ]
        }
    ]
}
